chartuno/__init__.py
chartuno-0.0.dist-info/METADATA
chartuno-0.0.dist-info/WHEEL
chartuno-0.0.dist-info/top_level.txt
chartuno-0.0.dist-info/RECORD
