Metadata-Version: 2.4
Name: chartuno
Version: 0.0
Summary: Coming soon
Author: ChartUno
